{
  "#id": 1039,
  "question": "Установите вклад в развитие биологии следующих учёных:\nОтвет запишите в виде сочетания букв и цифр, соблюдая алфавитную последовательность букв. Помните, что некоторые данные правого столбца (рисунка) могут использоваться несколько раз или не использоваться вообще. Например: А1Б2B1... .",
  "options": [
    [
      [
        "А",
        "Р. Вирхов"
      ],
      [
        "Б",
        "Э. Геккель"
      ],
      [
        "В",
        "И. И. Мечников"
      ]
    ],
    [
      [
        1,
        "открыл явление фагоцитоза"
      ],
      [
        2,
        "сформулировал правило экологической пирамиды"
      ],
      [
        3,
        "является одним из авторов биогенетического закона"
      ],
      [
        4,
        "дополнил клеточную теорию положением о том, что дочерние клетки образуются путем деления материнских клеток"
      ]
    ]
  ],
  "correct": "А4Б3В1",
  "is_test": false,
  "explaining": "Р. Вирхов дополнил клеточную теорию положением о том, что дочерние клетки образуются путем деления материнских клеток.\n\nЭ. Геккель вляется одним из авторов биогенетического закона.\n\nИ. И. Мечников открыл явление фагоцитоза.",
  "categories": [
    "mitosis"
  ],
  "attachments": {
    "question": [],
    "answer": []
  },
  "type": "correlate"
}