{
  "#id": 1057,
  "question": "Подберите недостающее понятие, учитывая, что между указанными парами существует одинаковая логическая связь:диффузия — поступление атмосферного воздуха = эндооцитоз — ?",
  "options": [
    [
      1,
      "пассивный транспорт"
    ],
    [
      2,
      "транспорт в мембранной упаковке"
    ],
    [
      3,
      "выделение продуктов азотистого обмена"
    ],
    [
      4,
      "поглощение чужеродных частиц лейкоцитами"
    ]
  ],
  "correct": 2,
  "is_test": true,
  "explaining": "Эндоцитоз — процесс захвата внешнего материала клеткой, осуществляемый путём образования мембранных пузырьков.",
  "categories": [
    "mitosis",
    "cytology"
  ],
  "attachments": {
    "question": [],
    "answer": []
  },
  "type": "test"
}