{
  "#id": 1566,
  "question": "Выберите отличительные признаки процессов пластического (I) и энергетического (II) обмена, а также признаки, общие для процессов обоих типов (III):\nа) происходит синтез сложных органических веществ;\nб) преобладают при физических нагрузках;\nв) энергия аккумулируется в виде макроэргичсских связей АТФ;\nг) катализируются ферментами;\nд) протекают с затра­тами энергии.",
  "options": [
    [
      1,
      "I — а, б; II — г, д; III — в"
    ],
    [
      2,
      "I — а, д; II — б, в; III — г"
    ],
    [
      3,
      "I — в, г; II — а, д; III — б"
    ],
    [
      4,
      "I — д; II — а, в; III — б, г"
    ]
  ],
  "correct": 2,
  "is_test": true,
  "explaining": "Пластический обмен (ассимиляция) — совокупность процессов образование органических веществ с использованием энергии в организме. Для пластического обмена характерны синтез сложных органических веществ (а), затраты энергии в ходе процесса (д), участие ферментов (г).\n\nДля энергетического обмена характерны запасание энергии в виде макроэргических связей АТФ (в), преобладание при физических нагрузках (б), участие ферментов (г).",
  "categories": [
    "chemistry"
  ],
  "attachments": {
    "question": [],
    "answer": []
  },
  "type": "test"
}