{
  "#id": 1593,
  "question": "Фрагмент молекулы ДНК (двойная спираль) имеет длину 68 нм и содержит 120 тимидиловых нуклеотидов. Рассчитайте процентное содержание гуаниловых нуклеотидов, входящих в состав данного фрагмента ДНК, учитывая, что один виток двойной спирали ДНК содержит 10 пар нуклеотидов и имеет длину 3,4 нм.\nОтвет запишите цифрами в виде целого числа без знака процентов, единицы измерения не указывайте. Например: 12.",
  "options": [],
  "correct": 20,
  "is_test": false,
  "explaining": "Во фрагменте ДНК длиной 68 нм 20 витков (68/3.4 = 20).\nВ 20 витках 200 пар нуклеотидов (20*10 = 200), то есть 400 нуклеотид\nУчитывая, что во фрагменте 120 тимидиловых нуклеотидов, то адениновых нуклеотидов тоже 120, а гуаниловых и цитидиловых нуклеотидов по 80 ((400-120*2)/2 = 80)\nРассчитываем процентное процентное содержание гуаниловых нуклеотидов 80/400 = 0,2 или 20%",
  "categories": [
    "mutability"
  ],
  "attachments": {
    "question": [],
    "answer": []
  },
  "type": "problem"
}