{
  "#id": 171,
  "question": "Организм, для которого характерно наличие двух ядер (большого и малого), изображён на рисунке:",
  "options": [
    [
      1,
      1
    ],
    [
      2,
      2
    ],
    [
      3,
      3
    ],
    [
      4,
      4
    ]
  ],
  "correct": 2,
  "is_test": true,
  "explaining": "Наличие двух ядер характерно для инфузорий. Они называются макро- и микронуклеус.",
  "categories": [
    "zoology"
  ],
  "attachments": {
    "question": [
      "423.png"
    ],
    "answer": []
  },
  "type": "test"
}