{
  "#id": 1775,
  "question": "У растений различают несколько жизненных форм. Три из четырех указанных растений представляют собой одну и ту же жизненную форму. Укажите растение, не входящее в эту группу:",
  "options": [
    [
      1,
      "огурец"
    ],
    [
      2,
      "клюква"
    ],
    [
      3,
      "морковь"
    ],
    [
      4,
      "одуванчик."
    ]
  ],
  "correct": 2,
  "is_test": true,
  "explaining": "",
  "categories": [
    "evolution"
  ],
  "attachments": {
    "question": [],
    "answer": []
  },
  "type": "test"
}