{
  "#id": 21,
  "question": "Желудок обозначен на схематическом рисунке цифрой:",
  "options": [
    [
      1,
      1
    ],
    [
      2,
      2
    ],
    [
      3,
      3
    ],
    [
      4,
      4
    ]
  ],
  "correct": 1,
  "is_test": true,
  "explaining": "На схематическом рисунке цифрами обозначены:\n1 — желудок; 2 — поджелудочная железа; 3 — печень; 4 — легкое",
  "categories": [
    "anatomy"
  ],
  "attachments": {
    "question": [
      "45.png"
    ],
    "answer": []
  },
  "type": "test"
}