{
  "#id": 375,
  "question": "Орган какой системы на схеме строения наземного моллюска обозначен цифрой 4?",
  "options": [
    [
      1,
      "нервной"
    ],
    [
      2,
      "кровеносной"
    ],
    [
      3,
      "дыхательной"
    ],
    [
      4,
      "пищеварительной"
    ]
  ],
  "correct": 2,
  "is_test": true,
  "explaining": "Под цифрой 4 обозначено сердце. Сердце является оганом кровеноснной системы.",
  "categories": [
    "zoology"
  ],
  "attachments": {
    "question": [
      "834.png"
    ],
    "answer": []
  },
  "type": "test"
}