{
  "#id": 393,
  "question": "У лабораторных мышей ген, влияющий на развитие волосяного покрова, сцеплен с геном, определяющим ширину лобной кости, и находится от него на расстоянии 14 морганид. Отсутствие волосяного покрова и формирование широкой лобной кости определяются рецессивными аутосомными генами. В эксперименте было проведено анализирующее скрещивание дигетерозиготной особи, гомозиготная мать которой имела нормальный волосяной покров и широкую лобную кость. Какова вероятность (%) рождения мышей без волосяного покрова и с широкой лобной костью?\nОтвет запишите цифрами в виде целого числа, единицы измерения не указывайте. Например: 12.",
  "options": [],
  "correct": 7,
  "is_test": false,
  "explaining": "а — отсутствие волосяного покрова, А — норма\nb — широкая лобная кость, В — норма\n\n*Так как между генами расстояние в 14 морганид, то кроссинговер между ними происходит с 14% вероятностью.\n\nанализирующее скрещивание\nP ааbb x aAbB (гомозиготная мать передала ей сцепленные аллели Аb)\nG ab     x  aB, Ab (некроссоверные гаметы, вероятность образования которых 43% для каждого типа) и аb, AB (кроссоверные гаметы, вероятность образования которых 7% для каждого типа).\n\nМышата без волосяного покрова и с широкой лобной костью(ааbb) родятся с 7% вероятность.",
  "categories": [
    "mutability"
  ],
  "attachments": {
    "question": [],
    "answer": []
  },
  "type": "problem"
}