{
  "#id": 442,
  "question": "Фрагмент молекулы ДНК содержит 480 тимидиловых нуклеотидов, что составляет 24% от общего количества нуклеотидов в этом фрагменте. Определите количество гуаниловых нуклеотидов, содержащихся в данном фрагменте ДНК.\nОтвет запишите цифрами в виде целого числа, единицы измерения не указывайте. Например: 12.",
  "options": [],
  "correct": 520,
  "is_test": false,
  "explaining": "Количество гуанинов всегда соответствует количеству цитозинов, а тиминов — аденину.\nТаким образом общее число тиминов и аденинов равно 960, что сотавляет 48%, тогда гуанинов и цитозинов 52%.  Количество гуанинов (52/2) получается равным 26% или 520 (960 · 0,26/0,48).",
  "categories": [
    "mutability"
  ],
  "attachments": {
    "question": [],
    "answer": []
  },
  "type": "problem"
}