{
  "#id": 498,
  "question": "На рисунка представлены схемы пищеварительных систем позвоночных животных. Определите, каким животным они соответствуют:\nОтвет запишите в виде сочетания букв и цифр, соблюдая алфавитную последовательность букв. Например: A4Б3B2Г1.",
  "options": [
    [
      [
        1,
        "сова"
      ],
      [
        2,
        "линь"
      ],
      [
        3,
        "жаба"
      ],
      [
        4,
        "хомяк"
      ]
    ]
  ],
  "correct": "А3Б1В4Г2",
  "is_test": false,
  "explaining": "Для хомяка как и других млекопитающих характерно наличие хорошо развитого желудка и толстой кишки.\nДля птиц в пищеварительном тракте появляется зоб.\nУ рыб первых появляются костные пластинки и зубы.\nУ земноводных появляются слюнные железы, обособленный желудок, тонкая и толстая кишка, клоаки.",
  "categories": [
    "anatomy"
  ],
  "attachments": {
    "question": [
      "995.png"
    ],
    "answer": []
  },
  "type": "correlate"
}