{
  "#id": 501,
  "question": "Живые организмы приспособлены к среде обитания; особенности их строения, жизнедеятельности и поведения соответствуют образу жизни. Это свойство живых организмов называется:",
  "options": [
    [
      1,
      "рост"
    ],
    [
      2,
      "дыхание"
    ],
    [
      3,
      "адаптация"
    ],
    [
      4,
      "раздражимость"
    ]
  ],
  "correct": 3,
  "is_test": true,
  "explaining": "Адаптация — приобретение признаков, необходимых для выживания в тех или иных условиях.",
  "categories": [
    "evolution",
    "mutability"
  ],
  "attachments": {
    "question": [],
    "answer": []
  },
  "type": "test"
}