{
  "#id": 568,
  "question": "Даны пять пар примеров органов (структур) живых организмов, три из которых могут служить одинаковым сравнительно-анатомическим доказательством эволюции:\nа — млечные железы козы и потовые железы человека\nб — спора бактерии и циста инфузории\nв — ласты тюленя и конечности крота\nг — крылья ушана и крылья майского жука\nд — почечные чешуи тополя и колючки кактуса\nУкажите, как называются эти три пары органов (структур) и какие два примера к ним не относятся («лишние»):",
  "options": [
    [
      1,
      "аналогичные органы; «лишние» примеры — а, б"
    ],
    [
      2,
      "аналогичные органы; «лишние» примеры — в,г"
    ],
    [
      3,
      "гомологичные органы; «лишние» примеры — б, г"
    ],
    [
      4,
      "гомологичные органы; «лишние» примеры — а, д"
    ]
  ],
  "correct": 3,
  "is_test": true,
  "explaining": "Гомологичные органы— это органы, имеющие сходное просихождение, но выпоняющие разные функции. Примеры б и г аналогичные органы.",
  "categories": [
    "evolution"
  ],
  "attachments": {
    "question": [],
    "answer": []
  },
  "type": "test"
}