{
  "#id": 599,
  "question": "Установите соответствие между веществами организма человека и их основными характеристиками:\nОтвет запишите в виде сочетания букв и цифр, соблюдая алфавитную последовательность букв левого столбца. Например: А1Б3B2Г4Д5.",
  "options": [
    [
      [
        "А",
        "рибоза"
      ],
      [
        "Б",
        "тромбин"
      ],
      [
        "В",
        "мальтаза"
      ],
      [
        "Г",
        "родопсин"
      ],
      [
        "Д",
        "соматотропин"
      ]
    ],
    [
      [
        1,
        "белок системы свертывания крови"
      ],
      [
        2,
        "светочувствительный пигмент клеток сетчатки глаза"
      ],
      [
        3,
        "фермент, расщепляющий дисахариды до моносахаридов"
      ],
      [
        4,
        "пептид, влияющий на развитие костной и хрящевой ткани"
      ],
      [
        5,
        "пятиуглеродный моносахарид, входящий в состав нуклеиновых кислот"
      ]
    ]
  ],
  "correct": "А5Б1В3Г2Д4",
  "is_test": false,
  "explaining": "Рибоза — пятиуглеродный моносахарид, входящий в состав РНК.\nТромбин — белок системы свертывания крови.\nМальтаза — фермент, расщепляющий дисахариды до моносахаридов.\nРодопсин — светочувствительный пигмент клеток сетчатки глаза.\nСоматотропин — пептид, влияющий на развитие костной и хрящевой ткани.",
  "categories": [
    "mitosis",
    "cytology"
  ],
  "attachments": {
    "question": [],
    "answer": []
  },
  "type": "correlate"
}