{
  "#id": 659,
  "question": "Выберите правильно составленную пару, определяющую разновидность геномной мутации и ее характеристику:",
  "options": [
    [
      1,
      "трисомия — образование зиготы 3n — 1"
    ],
    [
      2,
      "моносомия — образование зиготы 2n + 1"
    ],
    [
      3,
      "гексаплоидия — образование зиготы 6n"
    ],
    [
      4,
      "гетероплоидия — увеличение количества хромосом, кратное гаплоидному набору"
    ]
  ],
  "correct": 3,
  "is_test": true,
  "explaining": "Гексаплоидный организм - организм, клетки которого содержат шесть основных наборов хромосом.",
  "categories": [
    "evolution"
  ],
  "attachments": {
    "question": [],
    "answer": []
  },
  "type": "test"
}