{
  "#id": 871,
  "question": "У сосны обыкновенной:",
  "options": [
    [
      1,
      "нет корней"
    ],
    [
      2,
      "многосемянные плоды"
    ],
    [
      3,
      "в стебле имеются смоляные ходы"
    ],
    [
      4,
      "яйцеклетка развивается в зародышевом мешке"
    ]
  ],
  "correct": 3,
  "is_test": true,
  "explaining": "Сосна обыновенная относится к отделу Голосеменные. Для древесины хвойных пород характернымм являются смоляные ходы.",
  "categories": [
    "botanika"
  ],
  "attachments": {
    "question": [],
    "answer": []
  },
  "type": "test"
}