{
  "#id": 924,
  "question": "У речного окуня:",
  "options": [
    [
      1,
      "нет плавательного пузыря"
    ],
    [
      2,
      "постоянная температура тела"
    ],
    [
      3,
      "органы выделения - парные почки"
    ],
    [
      4,
      "плечевой пояс сочленен с позвоночником при помощи двух костей"
    ]
  ],
  "correct": 3,
  "is_test": true,
  "explaining": "Одной из отличительных особенностью рыб является наличие плавательного пузыря, непостоянная температура тела, парные почки",
  "categories": [
    "zoology"
  ],
  "attachments": {
    "question": [],
    "answer": []
  },
  "type": "test"
}